odoo/addons/account_payment_order_notification/README.rst
odoo/addons/account_payment_order_notification/__init__.py
odoo/addons/account_payment_order_notification/__manifest__.py
odoo/addons/account_payment_order_notification/data/mail_template_data.xml
odoo/addons/account_payment_order_notification/i18n/account_payment_order_notification.pot
odoo/addons/account_payment_order_notification/i18n/es.po
odoo/addons/account_payment_order_notification/i18n/fr.po
odoo/addons/account_payment_order_notification/models/__init__.py
odoo/addons/account_payment_order_notification/models/account_payment_order.py
odoo/addons/account_payment_order_notification/models/account_payment_order_notification.py
odoo/addons/account_payment_order_notification/readme/CONFIGURE.rst
odoo/addons/account_payment_order_notification/readme/CONTRIBUTORS.rst
odoo/addons/account_payment_order_notification/readme/DESCRIPTION.rst
odoo/addons/account_payment_order_notification/readme/USAGE.rst
odoo/addons/account_payment_order_notification/security/ir.model.access.csv
odoo/addons/account_payment_order_notification/static/description/icon.png
odoo/addons/account_payment_order_notification/static/description/index.html
odoo/addons/account_payment_order_notification/tests/__init__.py
odoo/addons/account_payment_order_notification/tests/test_account_payment_order_notification.py
odoo/addons/account_payment_order_notification/views/account_payment_order_notification_view.xml
odoo/addons/account_payment_order_notification/views/account_payment_order_view.xml
odoo/addons/account_payment_order_notification/wizard/__init__.py
odoo/addons/account_payment_order_notification/wizard/wizard_account_payment_order_notification.py
odoo/addons/account_payment_order_notification/wizard/wizard_account_payment_order_notification_views.xml
odoo14_addon_account_payment_order_notification-14.0.1.6.0.dist-info/METADATA
odoo14_addon_account_payment_order_notification-14.0.1.6.0.dist-info/WHEEL
odoo14_addon_account_payment_order_notification-14.0.1.6.0.dist-info/top_level.txt
odoo14_addon_account_payment_order_notification-14.0.1.6.0.dist-info/RECORD
